vigil_ai/__init__.py
vigil_ai/cache.py
vigil_ai/config.py
vigil_ai/debugger.py
vigil_ai/generator.py
vigil_ai/optimizer.py
vigil_ai/retry.py
vigil_ai/cli/ai_commands.py
vigil_ai/mcp/toolspec.yaml
vigil_ai/models/__init__.py
vigil_ai/models/_registry_init.py
vigil_ai/models/anthropic.py
vigil_ai/models/base.py
vigil_ai/models/huggingface.py
vigil_ai/models/registry.py
vigil_ai/tasks/__init__.py
vigil_ai/tasks/debugger.py
vigil_ai/tasks/generator.py
vigil_ai/tasks/optimizer.py
vigil_ai/tasks/selector.py
vigil_ai-0.3.0.dist-info/METADATA
vigil_ai-0.3.0.dist-info/WHEEL
vigil_ai-0.3.0.dist-info/licenses/LICENSE
vigil_ai-0.3.0.dist-info/RECORD
