Metadata-Version: 2.4
Name: vigil-ai
Version: 0.3.0
Summary: AI-powered workflow generation with foundation models (Claude, ESM, BioGPT, ChemBERTa, etc.)
Project-URL: Homepage, https://github.com/Science-Abundance/vigil
Project-URL: Documentation, https://github.com/Science-Abundance/vigil/tree/main/packages/vigil-core-ai
Project-URL: Repository, https://github.com/Science-Abundance/vigil
Project-URL: Issues, https://github.com/Science-Abundance/vigil/issues
Author: Science Abundance
License: Apache-2.0
License-File: LICENSE
Keywords: ai,claude,llm,pipeline,science,workflow
Classifier: Development Status :: 3 - Alpha
Classifier: Intended Audience :: Science/Research
Classifier: License :: OSI Approved :: Apache Software License
Classifier: Programming Language :: Python :: 3
Classifier: Programming Language :: Python :: 3.11
Classifier: Programming Language :: Python :: 3.12
Classifier: Programming Language :: Python :: 3.13
Requires-Python: >=3.11
Requires-Dist: anthropic>=0.18.0
Requires-Dist: rich>=14.0.0
Requires-Dist: vigil-core>=0.3.0
Provides-Extra: all
Requires-Dist: pyyaml>=6.0.0; extra == 'all'
Requires-Dist: sentencepiece>=0.1.99; extra == 'all'
Requires-Dist: torch>=2.0.0; extra == 'all'
Requires-Dist: transformers>=4.30.0; extra == 'all'
Provides-Extra: config
Requires-Dist: pyyaml>=6.0.0; extra == 'config'
Provides-Extra: dev
Requires-Dist: mypy>=1.0.0; extra == 'dev'
Requires-Dist: pytest-cov>=4.0.0; extra == 'dev'
Requires-Dist: pytest>=7.0.0; extra == 'dev'
Requires-Dist: pyyaml>=6.0.0; extra == 'dev'
Requires-Dist: ruff>=0.1.0; extra == 'dev'
Provides-Extra: science
Requires-Dist: sentencepiece>=0.1.99; extra == 'science'
Requires-Dist: torch>=2.0.0; extra == 'science'
Requires-Dist: transformers>=4.30.0; extra == 'science'
